wagtail_tagmanager/__init__.py
wagtail_tagmanager/apps.py
wagtail_tagmanager/bulk_actions.py
wagtail_tagmanager/forms.py
wagtail_tagmanager/models.py
wagtail_tagmanager/panels.py
wagtail_tagmanager/test_settings.py
wagtail_tagmanager/urls.py
wagtail_tagmanager/utils.py
wagtail_tagmanager/views.py
wagtail_tagmanager/viewsets.py
wagtail_tagmanager/migrations/__init__.py
wagtail_tagmanager/templates/wagtail_tagmanager/add_pages_to_tag.html
wagtail_tagmanager/templates/wagtail_tagmanager/confirm_merge_tags.html
wagtail_tagmanager/templates/wagtail_tagmanager/manage_tagged_objects.html
wagtail_tags-1.0.1.dist-info/licenses/LICENCE.txt
wagtail_tags-1.0.1.dist-info/METADATA
wagtail_tags-1.0.1.dist-info/WHEEL
wagtail_tags-1.0.1.dist-info/top_level.txt
wagtail_tags-1.0.1.dist-info/RECORD
