Metadata-Version: 2.4
Name: wagtail-tags
Version: 1.0.1
Summary: A Wagtail add-on for managing tags
Author: Mikhail Robinson, The Interaction Consortium
Maintainer: Mikhail Robinson, The Interaction Consortium
License-Expression: MIT
Project-URL: Homepage, https://github.com/mikhail-robinson/wagtail-tagmanager
Project-URL: Issues, https://github.com/mikhail-robinson/wagtail-tagmanager/issues
Classifier: Programming Language :: Python :: 3.8
Classifier: Programming Language :: Python :: 3.9
Classifier: Programming Language :: Python :: 3.10
Classifier: Programming Language :: Python :: 3.11
Classifier: Programming Language :: Python :: 3.12
Classifier: Programming Language :: Python :: 3.13
Classifier: Operating System :: OS Independent
Requires-Python: >=3.8
License-File: LICENCE.txt
Requires-Dist: wagtail>=5.2
Requires-Dist: django>=4.2
Dynamic: license-file
